MANIFEST.in
README.md
requirements.txt
setup.py
MedReportEval/__init__.py
MedReportEval/test.py
MedReportEval.egg-info/PKG-INFO
MedReportEval.egg-info/SOURCES.txt
MedReportEval.egg-info/dependency_links.txt
MedReportEval.egg-info/top_level.txt
MedReportEval/CXRMetric/__init__.py
MedReportEval/CXRMetric/evaluate_example.py
MedReportEval/CXRMetric/green.py
MedReportEval/CXRMetric/radgraph_evaluate_model.py
MedReportEval/CXRMetric/run_eval.py
MedReportEval/CXRMetric/run_eval_GREEN.py
MedReportEval/CXRMetric/test_GREEN.py
MedReportEval/CXRMetric/utils_GREEN.py
MedReportEval/CXRMetric/CheXbert/__init__.py
MedReportEval/CXRMetric/CheXbert/src/__init__.py
MedReportEval/CXRMetric/CheXbert/src/bert_tokenizer.py
MedReportEval/CXRMetric/CheXbert/src/constants.py
MedReportEval/CXRMetric/CheXbert/src/encode.py
MedReportEval/CXRMetric/CheXbert/src/label.py
MedReportEval/CXRMetric/CheXbert/src/label_GREEN.py
MedReportEval/CXRMetric/CheXbert/src/run_bert.py
MedReportEval/CXRMetric/CheXbert/src/sim.py
MedReportEval/CXRMetric/CheXbert/src/temp.py
MedReportEval/CXRMetric/CheXbert/src/unlabeled_dataset.py
MedReportEval/CXRMetric/CheXbert/src/utils.py
MedReportEval/CXRMetric/CheXbert/src/datasets/__init__.py
MedReportEval/CXRMetric/CheXbert/src/datasets/impressions_dataset.py
MedReportEval/CXRMetric/CheXbert/src/datasets/unlabeled_dataset.py
MedReportEval/CXRMetric/CheXbert/src/models/__init__.py
MedReportEval/CXRMetric/CheXbert/src/models/bert_encoder.py
MedReportEval/CXRMetric/CheXbert/src/models/bert_labeler.py
MedReportEval/CXRMetric/dygiepp/__init__.py
MedReportEval/CXRMetric/dygiepp/dygie/__init__.py
MedReportEval/CXRMetric/dygiepp/dygie/data/__init__.py
MedReportEval/CXRMetric/dygiepp/dygie/models/__init__.py
MedReportEval/CXRMetric/dygiepp/dygie/models/coref.py
MedReportEval/CXRMetric/dygiepp/dygie/models/dygie.py
MedReportEval/CXRMetric/dygiepp/dygie/models/entity_beam_pruner.py
MedReportEval/CXRMetric/dygiepp/dygie/models/events.py
MedReportEval/CXRMetric/dygiepp/dygie/models/ner.py
MedReportEval/CXRMetric/dygiepp/dygie/models/relation.py
MedReportEval/CXRMetric/dygiepp/dygie/models/shared.py
