Metadata-Version: 2.1
Name: MedReportEval
Version: 0.0.6
Summary: A brief description of your package
License: MIT
Classifier: Development Status :: 1 - Planning
Classifier: Programming Language :: Python :: 3
Classifier: License :: OSI Approved :: MIT License
Classifier: Operating System :: OS Independent
Requires-Python: >=3.6
